afaanoromo_tokenizer/__init__.py
afaanoromo_tokenizer/ao_tokenizer.py
afaanoromo_tokenizer/bpe_tokenizer.json
afaanoromo_tokenizer/unigram_tokenizer.json
afaanoromo_tokenizer/wordpiece_tokenizer.json
afaanoromo_tokenizer-1.1.3.dist-info/licenses/LICENSE
afaanoromo_tokenizer-1.1.3.dist-info/METADATA
afaanoromo_tokenizer-1.1.3.dist-info/WHEEL
afaanoromo_tokenizer-1.1.3.dist-info/top_level.txt
afaanoromo_tokenizer-1.1.3.dist-info/RECORD
