Metadata-Version: 2.4
Name: afaanoromo_tokenizer
Version: 1.1.3
Summary: Tokenizer library for Afaan Oromo supporting Unigram, BPE, and WordPiece algorithms.
Author-email: Eyasu Saketa and Abebe Zerihun <eyasusaketa@gmail.com>
License: MIT
Classifier: Programming Language :: Python :: 3
Classifier: License :: OSI Approved :: MIT License
Classifier: Topic :: Text Processing :: Linguistic
Classifier: Topic :: Software Development :: Libraries :: Python Modules
Classifier: Intended Audience :: Science/Research
Requires-Python: >=3.7
License-File: LICENSE
Requires-Dist: tokenizers>=0.15.0
Requires-Dist: transformers>=4.30.0
Requires-Dist: numpy
Requires-Dist: tqdm
Dynamic: license-file
